<?xml version="1.0" encoding="utf-8"?>
<odoo>
    <template id="wspay_form">
        <div>
            <input type="hidden" name="data_set" t-att-data-action-url="tx_url" data-remove-me=""/>
            <input type="hidden" name="ShopID" t-att-value="ShopID"/>
            <input type="hidden" name="ShoppingCartID" t-att-value="ShoppingCartID"/>
            <input type="hidden" name="TotalAmount" t-att-value="TotalAmount"/>
            <input type="hidden" name="Signature" t-att-value="Signature"/>
            <input type="hidden" name="Lang" t-att-value="Lang"/>
            <input type="hidden" name="CustomerFirstName" t-att-value="CustomerFirstName"/>
            <input type="hidden" name="CustomerLastName" t-att-value="CustomerLastName"/>
            <input type="hidden" name="CustomerAddress" t-att-value="CustomerAddress"/>
            <input type="hidden" name="CustomerCity" t-att-value="CustomerCity"/>
            <input type="hidden" name="CustomerZIP" t-att-value="CustomerZIP"/>
            <input type="hidden" name="CustomerCountry" t-att-value="CustomerCountry"/>
            <input type="hidden" name="CustomerEmail" t-att-value="CustomerEmail"/>
            <input type="hidden" name="CustomerPhone" t-att-value="CustomerPhone"/>
            <!-- URLs -->
            <input type="hidden" name='ReturnURL' t-att-value="ReturnURL"/>
            <input type="hidden" name='CancelURL' t-att-value="CancelURL"/>
            <input type="hidden" name="ReturnErrorURL" t-att-value="ReturnErrorURL"/>
        </div>
    </template>
</odoo>
